{
  "2020": {
    "Natural Gas": 38683.9,
    "Solar": 12785.2,
    "Water": 12661.6,
    "Wind": 6041.8,
    "Geothermal": 2654.8,
    "Nuclear": 2323.0,
    "Wood Waste Solids": 597.5,
    "Landfill Gas": 289.5,
    "Other Gas": 258.1,
    "Electricity used for energy storage": 252.5,
    "Jet Fuel": 223.5,
    "Other Biomass Gases ": 143.8,
    "Disillate Fuel Oil": 125.0,
    "Waste Heat": 123.6,
    "Municipal Solid Waste (All)": 59.6,
    "Refined Coal": 55.0,
    "Agriculture Byproducts": 29.1,
    "Petroleum Coke": 27.3,
    "Purchased Steam": 8.0,
    "Gaseous Propane": 2.3
  },
  "2021": {
    "Natural Gas": 40233.7,
    "Solar": 14327.8,
    "Water": 12859.3,
    "Wind": 5912.5,
    "Geothermal": 2670.8,
    "Nuclear": 2323.0,
    "Electricity used for energy storage": 657.8,
    "Wood Waste Solids": 578.0,
    "Landfill Gas": 286.6,
    "Other Gas": 250.1,
    "Jet Fuel": 149.0,
    "Other Biomass Gases ": 146.3,
    "Disillate Fuel Oil": 125.0,
    "Waste Heat": 123.6,
    "Municipal Solid Waste (All)": 59.6,
    "Refined Coal": 55.0,
    "Agriculture Byproducts": 29.1,
    "Petroleum Coke": 27.3,
    "Purchased Steam": 8.0,
    "Gaseous Propane": 1.9,
    "Other": 1.0
  },
  "2022": {
    "Natural Gas": 40282.3,
    "Solar": 15573.9,
    "Water": 12293.2,
    "Wind": 6170.3,
    "Geothermal": 2670.8,
    "Electricity used for energy storage": 2468.5,
    "Nuclear": 2323.0,
    "Wood Waste Solids": 583.0,
    "Landfill Gas": 281.4,
    "Other Gas": 250.1,
    "Other Biomass Gases ": 150.7,
    "Jet Fuel": 149.0,
    "Disillate Fuel Oil": 125.0,
    "Waste Heat": 123.6,
    "Municipal Solid Waste (All)": 59.6,
    "Bituminous Coal": 55.0,
    "Agriculture Byproducts": 29.1,
    "Petroleum Coke": 27.3,
    "Purchased Steam": 8.0,
    "Gaseous Propane": 1.9,
    "Other": 1.0
  },
  "2023": {
    "Natural Gas": 40425.1,
    "Solar": 17674.2,
    "Water": 12316.1,
    "Wind": 6248.9,
    "Electricity used for energy storage": 5000.7,
    "Geothermal": 2709.7,
    "Nuclear": 2323.0,
    "Wood Waste Solids": 558.0,
    "Landfill Gas": 277.1,
    "Other Gas": 244.6,
    "Other Biomass Gases ": 153.7,
    "Jet Fuel": 149.0,
    "Disillate Fuel Oil": 120.5,
    "Waste Heat": 89.6,
    "Municipal Solid Waste (All)": 59.6,
    "Bituminous Coal": 55.0,
    "Agriculture Byproducts": 33.1,
    "Purchased Steam": 8.0,
    "Gaseous Propane": 1.9,
    "Other": 1.0
  },
  "2024": {
    "Natural Gas": 39434.1,
    "Solar": 19964.2,
    "Water": 12099.6,
    "Electricity used for energy storage": 8036.2,
    "Wind": 6330.7,
    "Geothermal": 2650.3,
    "Nuclear": 2323.0,
    "Wood Waste Solids": 530.0,
    "Landfill Gas": 277.1,
    "Other Gas": 244.6,
    "Other Biomass Gases ": 165.2,
    "Jet Fuel": 149.0,
    "Disillate Fuel Oil": 120.5,
    "Waste Heat": 62.3,
    "Municipal Solid Waste (All)": 59.6,
    "Bituminous Coal": 55.0,
    "Agriculture Byproducts": 33.1,
    "Purchased Steam": 8.0,
    "Other": 5.0,
    "Gaseous Propane": 1.8
  },
  "2025": {
    "Natural Gas": 39458.5,
    "Solar": 22569.9,
    "Water": 12097.9,
    "Electricity used for energy storage": 11751.0,
    "Wind": 6469.7,
    "Geothermal": 2650.3,
    "Nuclear": 2323.0,
    "Wood Waste Solids": 412.5,
    "Landfill Gas": 277.1,
    "Other Gas": 244.6,
    "Other Biomass Gases ": 165.2,
    "Jet Fuel": 149.0,
    "Disillate Fuel Oil": 120.5,
    "Waste Heat": 62.3,
    "Bituminous Coal": 55.0,
    "Agriculture Byproducts": 33.1,
    "Purchased Steam": 8.0,
    "Other": 5.0,
    "Gaseous Propane": 1.8
  }
}